metaflow_extensions/measure/plugins/datadog_decorator.py
metaflow_extensions/measure/plugins/dogstatsd_manager.py
metaflow_extensions/measure/plugins/measure.py
metaflow_extensions/measure/plugins/mfextinit_org.py
metaflow_extensions/measure/plugins/datadog/__init__.py
metaflow_extensions/measure/plugins/datadog/py.typed
metaflow_extensions/measure/plugins/datadog/version.py
metaflow_extensions/measure/plugins/datadog/dogstatsd/__init__.py
metaflow_extensions/measure/plugins/datadog/dogstatsd/base.py
metaflow_extensions/measure/plugins/datadog/dogstatsd/container.py
metaflow_extensions/measure/plugins/datadog/dogstatsd/context.py
metaflow_extensions/measure/plugins/datadog/dogstatsd/context_async.py
metaflow_extensions/measure/plugins/datadog/dogstatsd/route.py
metaflow_extensions/measure/plugins/datadog/util/__init__.py
metaflow_extensions/measure/plugins/datadog/util/cli.py
metaflow_extensions/measure/plugins/datadog/util/compat.py
metaflow_extensions/measure/plugins/datadog/util/config.py
metaflow_extensions/measure/plugins/datadog/util/deprecation.py
metaflow_extensions/measure/plugins/datadog/util/format.py
metaflow_extensions/measure/plugins/datadog/util/hostname.py
metaflow_measure-0.0.3.dist-info/LICENSE
metaflow_measure-0.0.3.dist-info/METADATA
metaflow_measure-0.0.3.dist-info/WHEEL
metaflow_measure-0.0.3.dist-info/top_level.txt
metaflow_measure-0.0.3.dist-info/RECORD
